python_zaqarclient-4.3.0.dist-info/licenses/AUTHORS
python_zaqarclient-4.3.0.dist-info/licenses/LICENSE
zaqarclient/__init__.py
zaqarclient/_i18n.py
zaqarclient/errors.py
zaqarclient/version.py
zaqarclient/auth/__init__.py
zaqarclient/auth/base.py
zaqarclient/auth/keystone.py
zaqarclient/auth/signed_url.py
zaqarclient/common/__init__.py
zaqarclient/common/decorators.py
zaqarclient/common/http.py
zaqarclient/queues/__init__.py
zaqarclient/queues/cli.py
zaqarclient/queues/client.py
zaqarclient/queues/v2/__init__.py
zaqarclient/queues/v2/api.py
zaqarclient/queues/v2/claim.py
zaqarclient/queues/v2/cli.py
zaqarclient/queues/v2/client.py
zaqarclient/queues/v2/core.py
zaqarclient/queues/v2/flavor.py
zaqarclient/queues/v2/iterator.py
zaqarclient/queues/v2/message.py
zaqarclient/queues/v2/pool.py
zaqarclient/queues/v2/queues.py
zaqarclient/queues/v2/subscription.py
zaqarclient/tests/__init__.py
zaqarclient/tests/base.py
zaqarclient/tests/mock/__init__.py
zaqarclient/tests/mock/message.py
zaqarclient/tests/queues/__init__.py
zaqarclient/tests/queues/base.py
zaqarclient/tests/queues/claims.py
zaqarclient/tests/queues/flavor.py
zaqarclient/tests/queues/health.py
zaqarclient/tests/queues/messages.py
zaqarclient/tests/queues/pool.py
zaqarclient/tests/queues/queues.py
zaqarclient/tests/queues/subscriptions.py
zaqarclient/tests/transport/__init__.py
zaqarclient/tests/transport/api.py
zaqarclient/tests/transport/dummy.py
zaqarclient/transport/__init__.py
zaqarclient/transport/api.py
zaqarclient/transport/base.py
zaqarclient/transport/errors.py
zaqarclient/transport/http.py
zaqarclient/transport/request.py
zaqarclient/transport/response.py
zaqarclient/transport/ws.py
python_zaqarclient-4.3.0.dist-info/METADATA
python_zaqarclient-4.3.0.dist-info/WHEEL
python_zaqarclient-4.3.0.dist-info/entry_points.txt
python_zaqarclient-4.3.0.dist-info/pbr.json
python_zaqarclient-4.3.0.dist-info/top_level.txt
python_zaqarclient-4.3.0.dist-info/RECORD
