Metadata-Version: 2.4
Name: python-zaqarclient
Version: 4.3.0
Summary: Client Library for OpenStack Zaqar Messaging API
Home-page: https://docs.openstack.org/python-zaqarclient/latest/
Author: OpenStack
Author-email: openstack-discuss@lists.openstack.org
Classifier: Environment :: Console
Classifier: Environment :: OpenStack
Classifier: Intended Audience :: Information Technology
Classifier: Intended Audience :: Developers
Classifier: Intended Audience :: System Administrators
Classifier: License :: OSI Approved :: Apache Software License
Classifier: Operating System :: POSIX :: Linux
Classifier: Programming Language :: Python
Classifier: Programming Language :: Python :: Implementation :: CPython
Classifier: Programming Language :: Python :: 3 :: Only
Classifier: Programming Language :: Python :: 3
Classifier: Programming Language :: Python :: 3.10
Classifier: Programming Language :: Python :: 3.11
Classifier: Programming Language :: Python :: 3.12
Requires-Python: >=3.10
License-File: LICENSE
License-File: AUTHORS
Requires-Dist: pbr!=2.1.0,>=2.0.0
Requires-Dist: requests>=2.14.2
Requires-Dist: stevedore>=1.20.0
Requires-Dist: jsonschema>=3.2.0
Requires-Dist: oslo.i18n>=3.15.3
Requires-Dist: oslo.log>=3.36.0
Requires-Dist: oslo.utils>=3.33.0
Requires-Dist: keystoneauth1>=3.4.0
Requires-Dist: osc-lib>=2.1.0
Dynamic: author
Dynamic: author-email
Dynamic: classifier
Dynamic: description
Dynamic: home-page
Dynamic: license-file
Dynamic: requires-dist
Dynamic: requires-python
Dynamic: summary
